[
    {
        "name": "Smile",
        "image": "https://fonts.gstatic.com/s/e/notoemoji/latest/1f600/emoji.svg"
    },
    {
        "name": "Smile-with-big-eyes",
        "image": "https://fonts.gstatic.com/s/e/notoemoji/latest/1f603/emoji.svg"
    },
    {
        "name": "Grin",
        "image": "https://fonts.gstatic.com/s/e/notoemoji/latest/1f604/emoji.svg"
    },
    {
        "name": "Grinning",
        "image": "https://fonts.gstatic.com/s/e/notoemoji/latest/1f601/emoji.svg"
    },
    {
        "name": "Laughing",
        "image": "https://fonts.gstatic.com/s/e/notoemoji/latest/1f606/emoji.svg"
    },
    {
        "name": "Grin-sweat",
        "image": "https://fonts.gstatic.com/s/e/notoemoji/latest/1f605/emoji.svg"
    },
    {
        "name": "Joy",
        "image": "https://fonts.gstatic.com/s/e/notoemoji/latest/1f602/emoji.svg"
    },
    {
        "name": "Rofl",
        "image": "https://fonts.gstatic.com/s/e/notoemoji/latest/1f923/emoji.svg"
    },
    {
        "name": "Loudly-crying",
        "image": "https://fonts.gstatic.com/s/e/notoemoji/latest/1f62d/emoji.svg"
    },
    {
        "name": "Wink",
        "image": "https://fonts.gstatic.com/s/e/notoemoji/latest/1f609/emoji.svg"
    },
    {
        "name": "Kissing",
        "image": "https://fonts.gstatic.com/s/e/notoemoji/latest/1f617/emoji.svg"
    },
    {
        "name": "Kissing-smiling-eyes",
        "image": "https://fonts.gstatic.com/s/e/notoemoji/latest/1f619/emoji.svg"
    },
    {
        "name": "Kissing-closed-eyes",
        "image": "https://fonts.gstatic.com/s/e/notoemoji/latest/1f61a/emoji.svg"
    },
    {
        "name": "Kissing-heart",
        "image": "https://fonts.gstatic.com/s/e/notoemoji/latest/1f618/emoji.svg"
    },
    {
        "name": "Heart-face",
        "image": "https://fonts.gstatic.com/s/e/notoemoji/latest/1f970/emoji.svg"
    },
    {
        "name": "Heart-eyes",
        "image": "https://fonts.gstatic.com/s/e/notoemoji/latest/1f60d/emoji.svg"
    },
    {
        "name": "Star-struck",
        "image": "https://fonts.gstatic.com/s/e/notoemoji/latest/1f929/emoji.svg"
    },
    {
        "name": "Partying-face",
        "image": "https://fonts.gstatic.com/s/e/notoemoji/latest/1f973/emoji.svg"
    },
    {
        "name": "Melting",
        "image": "https://fonts.gstatic.com/s/e/notoemoji/latest/1fae0/emoji.svg"
    },
    {
        "name": "Upside-down-face",
        "image": "https://fonts.gstatic.com/s/e/notoemoji/latest/1f643/emoji.svg"
    },
    {
        "name": "Slightly-happy",
        "image": "https://fonts.gstatic.com/s/e/notoemoji/latest/1f642/emoji.svg"
    },
    {
        "name": "Happy-cry",
        "image": "https://fonts.gstatic.com/s/e/notoemoji/latest/1f972/emoji.svg"
    },
    {
        "name": "Holding-back-tears",
        "image": "https://fonts.gstatic.com/s/e/notoemoji/latest/1f979/emoji.svg"
    },
    {
        "name": "Blush",
        "image": "https://fonts.gstatic.com/s/e/notoemoji/latest/1f60a/emoji.svg"
    },
    {
        "name": "Warm-smile",
        "image": "https://fonts.gstatic.com/s/e/notoemoji/latest/263a_fe0f/emoji.svg"
    },
    {
        "name": "Relieved",
        "image": "https://fonts.gstatic.com/s/e/notoemoji/latest/1f60c/emoji.svg"
    },
    {
        "name": "Smirk",
        "image": "https://fonts.gstatic.com/s/e/notoemoji/latest/1f60f/emoji.svg"
    },
    {
        "name": "Drool",
        "image": "https://fonts.gstatic.com/s/e/notoemoji/latest/1f924/emoji.svg"
    },
    {
        "name": "Yum",
        "image": "https://fonts.gstatic.com/s/e/notoemoji/latest/1f60b/emoji.svg"
    },
    {
        "name": "Stuck-out-tongue",
        "image": "https://fonts.gstatic.com/s/e/notoemoji/latest/1f61b/emoji.svg"
    },
    {
        "name": "Squinting-tongue",
        "image": "https://fonts.gstatic.com/s/e/notoemoji/latest/1f61d/emoji.svg"
    },
    {
        "name": "Winky-tongue",
        "image": "https://fonts.gstatic.com/s/e/notoemoji/latest/1f61c/emoji.svg"
    },
    {
        "name": "Zany-face",
        "image": "https://fonts.gstatic.com/s/e/notoemoji/latest/1f92a/emoji.svg"
    },
    {
        "name": "Woozy",
        "image": "https://fonts.gstatic.com/s/e/notoemoji/latest/1f974/emoji.svg"
    },
    {
        "name": "Pensive",
        "image": "https://fonts.gstatic.com/s/e/notoemoji/latest/1f614/emoji.svg"
    },
    {
        "name": "Pleading",
        "image": "https://fonts.gstatic.com/s/e/notoemoji/latest/1f97a/emoji.svg"
    },
    {
        "name": "Grimacing",
        "image": "https://fonts.gstatic.com/s/e/notoemoji/latest/1f62c/emoji.svg"
    },
    {
        "name": "Expressionless",
        "image": "https://fonts.gstatic.com/s/e/notoemoji/latest/1f611/emoji.svg"
    },
    {
        "name": "Neutral-face",
        "image": "https://fonts.gstatic.com/s/e/notoemoji/latest/1f610/emoji.svg"
    },
    {
        "name": "Mouth-none",
        "image": "https://fonts.gstatic.com/s/e/notoemoji/latest/1f636/emoji.svg"
    },
    {
        "name": "Face-in-clouds",
        "image": "https://fonts.gstatic.com/s/e/notoemoji/latest/1f636_200d_1f32b_fe0f/emoji.svg"
    },
    {
        "name": "Dotted-line-face",
        "image": "https://fonts.gstatic.com/s/e/notoemoji/latest/1fae5/emoji.svg"
    },
    {
        "name": "Zipper-face",
        "image": "https://fonts.gstatic.com/s/e/notoemoji/latest/1f910/emoji.svg"
    },
    {
        "name": "Salute",
        "image": "https://fonts.gstatic.com/s/e/notoemoji/latest/1fae1/emoji.svg"
    },
    {
        "name": "Thinking-face",
        "image": "https://fonts.gstatic.com/s/e/notoemoji/latest/1f914/emoji.svg"
    },
    {
        "name": "Shushing-face",
        "image": "https://fonts.gstatic.com/s/e/notoemoji/latest/1f92b/emoji.svg"
    },
    {
        "name": "Hand-over-mouth",
        "image": "https://fonts.gstatic.com/s/e/notoemoji/latest/1fae2/emoji.svg"
    },
    {
        "name": "Smiling-eyes-with-hand-over-mouth",
        "image": "https://fonts.gstatic.com/s/e/notoemoji/latest/1f92d/emoji.svg"
    },
    {
        "name": "Yawn",
        "image": "https://fonts.gstatic.com/s/e/notoemoji/latest/1f971/emoji.svg"
    },
    {
        "name": "Hug-face",
        "image": "https://fonts.gstatic.com/s/e/notoemoji/latest/1f917/emoji.svg"
    },
    {
        "name": "Peeking",
        "image": "https://fonts.gstatic.com/s/e/notoemoji/latest/1fae3/emoji.svg"
    },
    {
        "name": "Screaming",
        "image": "https://fonts.gstatic.com/s/e/notoemoji/latest/1f631/emoji.svg"
    },
    {
        "name": "Raised-eyebrow",
        "image": "https://fonts.gstatic.com/s/e/notoemoji/latest/1f928/emoji.svg"
    },
    {
        "name": "Monocle",
        "image": "https://fonts.gstatic.com/s/e/notoemoji/latest/1f9d0/emoji.svg"
    },
    {
        "name": "Unamused",
        "image": "https://fonts.gstatic.com/s/e/notoemoji/latest/1f612/emoji.svg"
    },
    {
        "name": "Rolling-eyes",
        "image": "https://fonts.gstatic.com/s/e/notoemoji/latest/1f644/emoji.svg"
    },
    {
        "name": "Exhale",
        "image": "https://fonts.gstatic.com/s/e/notoemoji/latest/1f62e_200d_1f4a8/emoji.svg"
    },
    {
        "name": "Triumph",
        "image": "https://fonts.gstatic.com/s/e/notoemoji/latest/1f624/emoji.svg"
    },
    {
        "name": "Angry",
        "image": "https://fonts.gstatic.com/s/e/notoemoji/latest/1f620/emoji.svg"
    },
    {
        "name": "Rage",
        "image": "https://fonts.gstatic.com/s/e/notoemoji/latest/1f621/emoji.svg"
    },
    {
        "name": "Cursing",
        "image": "https://fonts.gstatic.com/s/e/notoemoji/latest/1f92c/emoji.svg"
    },
    {
        "name": "Sad",
        "image": "https://fonts.gstatic.com/s/e/notoemoji/latest/1f61e/emoji.svg"
    },
    {
        "name": "Sweat",
        "image": "https://fonts.gstatic.com/s/e/notoemoji/latest/1f613/emoji.svg"
    },
    {
        "name": "Worried",
        "image": "https://fonts.gstatic.com/s/e/notoemoji/latest/1f61f/emoji.svg"
    },
    {
        "name": "Concerned",
        "image": "https://fonts.gstatic.com/s/e/notoemoji/latest/1f625/emoji.svg"
    },
    {
        "name": "Cry",
        "image": "https://fonts.gstatic.com/s/e/notoemoji/latest/1f622/emoji.svg"
    },
    {
        "name": "Big-frown",
        "image": "https://fonts.gstatic.com/s/e/notoemoji/latest/2639_fe0f/emoji.svg"
    },
    {
        "name": "Frown",
        "image": "https://fonts.gstatic.com/s/e/notoemoji/latest/1f641/emoji.svg"
    },
    {
        "name": "Diagonal-mouth",
        "image": "https://fonts.gstatic.com/s/e/notoemoji/latest/1fae4/emoji.svg"
    },
    {
        "name": "Slightly-frowning",
        "image": "https://fonts.gstatic.com/s/e/notoemoji/latest/1f615/emoji.svg"
    },
    {
        "name": "Anxious-with-sweat",
        "image": "https://fonts.gstatic.com/s/e/notoemoji/latest/1f630/emoji.svg"
    },
    {
        "name": "Scared",
        "image": "https://fonts.gstatic.com/s/e/notoemoji/latest/1f628/emoji.svg"
    },
    {
        "name": "Anguished",
        "image": "https://fonts.gstatic.com/s/e/notoemoji/latest/1f627/emoji.svg"
    },
    {
        "name": "Gasp",
        "image": "https://fonts.gstatic.com/s/e/notoemoji/latest/1f626/emoji.svg"
    },
    {
        "name": "Mouth-open",
        "image": "https://fonts.gstatic.com/s/e/notoemoji/latest/1f62e/emoji.svg"
    },
    {
        "name": "Surprised",
        "image": "https://fonts.gstatic.com/s/e/notoemoji/latest/1f62f/emoji.svg"
    },
    {
        "name": "Astonished",
        "image": "https://fonts.gstatic.com/s/e/notoemoji/latest/1f632/emoji.svg"
    },
    {
        "name": "Flushed",
        "image": "https://fonts.gstatic.com/s/e/notoemoji/latest/1f633/emoji.svg"
    },
    {
        "name": "Mind-blown",
        "image": "https://fonts.gstatic.com/s/e/notoemoji/latest/1f92f/emoji.svg"
    },
    {
        "name": "Scrunched-mouth",
        "image": "https://fonts.gstatic.com/s/e/notoemoji/latest/1f616/emoji.svg"
    },
    {
        "name": "Scrunched-eyes",
        "image": "https://fonts.gstatic.com/s/e/notoemoji/latest/1f623/emoji.svg"
    },
    {
        "name": "Weary",
        "image": "https://fonts.gstatic.com/s/e/notoemoji/latest/1f629/emoji.svg"
    },
    {
        "name": "Distraught",
        "image": "https://fonts.gstatic.com/s/e/notoemoji/latest/1f62b/emoji.svg"
    },
    {
        "name": "X-eyes",
        "image": "https://fonts.gstatic.com/s/e/notoemoji/latest/1f635/emoji.svg"
    },
    {
        "name": "Dizzy-face",
        "image": "https://fonts.gstatic.com/s/e/notoemoji/latest/1f635_200d_1f4ab/emoji.svg"
    },
    {
        "name": "Shaking-face",
        "image": "https://fonts.gstatic.com/s/e/notoemoji/latest/1fae8/emoji.svg"
    },
    {
        "name": "Cold-face",
        "image": "https://fonts.gstatic.com/s/e/notoemoji/latest/1f976/emoji.svg"
    },
    {
        "name": "Hot-face",
        "image": "https://fonts.gstatic.com/s/e/notoemoji/latest/1f975/emoji.svg"
    },
    {
        "name": "Sick",
        "image": "https://fonts.gstatic.com/s/e/notoemoji/latest/1f922/emoji.svg"
    },
    {
        "name": "Vomit",
        "image": "https://fonts.gstatic.com/s/e/notoemoji/latest/1f92e/emoji.svg"
    },
    {
        "name": "Sleep",
        "image": "https://fonts.gstatic.com/s/e/notoemoji/latest/1f634/emoji.svg"
    },
    {
        "name": "Sleepy",
        "image": "https://fonts.gstatic.com/s/e/notoemoji/latest/1f62a/emoji.svg"
    },
    {
        "name": "Sneeze",
        "image": "https://fonts.gstatic.com/s/e/notoemoji/latest/1f927/emoji.svg"
    },
    {
        "name": "Thermometer-face",
        "image": "https://fonts.gstatic.com/s/e/notoemoji/latest/1f912/emoji.svg"
    },
    {
        "name": "Bandage-face",
        "image": "https://fonts.gstatic.com/s/e/notoemoji/latest/1f915/emoji.svg"
    },
    {
        "name": "Mask",
        "image": "https://fonts.gstatic.com/s/e/notoemoji/latest/1f637/emoji.svg"
    },
    {
        "name": "Liar",
        "image": "https://fonts.gstatic.com/s/e/notoemoji/latest/1f925/emoji.svg"
    },
    {
        "name": "Halo",
        "image": "https://fonts.gstatic.com/s/e/notoemoji/latest/1f607/emoji.svg"
    },
    {
        "name": "Cowboy",
        "image": "https://fonts.gstatic.com/s/e/notoemoji/latest/1f920/emoji.svg"
    },
    {
        "name": "Money-face",
        "image": "https://fonts.gstatic.com/s/e/notoemoji/latest/1f911/emoji.svg"
    },
    {
        "name": "Nerd-face",
        "image": "https://fonts.gstatic.com/s/e/notoemoji/latest/1f913/emoji.svg"
    },
    {
        "name": "Sunglasses-face",
        "image": "https://fonts.gstatic.com/s/e/notoemoji/latest/1f60e/emoji.svg"
    },
    {
        "name": "Disguise",
        "image": "https://fonts.gstatic.com/s/e/notoemoji/latest/1f978/emoji.svg"
    },
    {
        "name": "Clown",
        "image": "https://fonts.gstatic.com/s/e/notoemoji/latest/1f921/emoji.svg"
    },
    {
        "name": "Imp-smile",
        "image": "https://fonts.gstatic.com/s/e/notoemoji/latest/1f608/emoji.svg"
    },
    {
        "name": "Imp-frown",
        "image": "https://fonts.gstatic.com/s/e/notoemoji/latest/1f47f/emoji.svg"
    },
    {
        "name": "Ghost",
        "image": "https://fonts.gstatic.com/s/e/notoemoji/latest/1f47b/emoji.svg"
    },
    {
        "name": "Skull",
        "image": "https://fonts.gstatic.com/s/e/notoemoji/latest/1f480/emoji.svg"
    },
    {
        "name": "Jack-o-lantern",
        "image": "https://fonts.gstatic.com/s/e/notoemoji/latest/1f383/emoji.svg"
    },
    {
        "name": "Poop",
        "image": "https://fonts.gstatic.com/s/e/notoemoji/latest/1f4a9/emoji.svg"
    },
    {
        "name": "Robot",
        "image": "https://fonts.gstatic.com/s/e/notoemoji/latest/1f916/emoji.svg"
    },
    {
        "name": "Alien",
        "image": "https://fonts.gstatic.com/s/e/notoemoji/latest/1f47d/emoji.svg"
    },
    {
        "name": "Sun-with-face",
        "image": "https://fonts.gstatic.com/s/e/notoemoji/latest/1f31e/emoji.svg"
    },
    {
        "name": "Moon-face-first-quarter",
        "image": "https://fonts.gstatic.com/s/e/notoemoji/latest/1f31b/emoji.svg"
    },
    {
        "name": "Moon-face-last-quarter",
        "image": "https://fonts.gstatic.com/s/e/notoemoji/latest/1f31c/emoji.svg"
    },
    {
        "name": "See-no-evil-monkey",
        "image": "https://fonts.gstatic.com/s/e/notoemoji/latest/1f648/emoji.svg"
    },
    {
        "name": "Hear-no-evil-monkey",
        "image": "https://fonts.gstatic.com/s/e/notoemoji/latest/1f649/emoji.svg"
    },
    {
        "name": "Speak-no-evil-monkey",
        "image": "https://fonts.gstatic.com/s/e/notoemoji/latest/1f64a/emoji.svg"
    },
    {
        "name": "Smiley-cat",
        "image": "https://fonts.gstatic.com/s/e/notoemoji/latest/1f63a/emoji.svg"
    },
    {
        "name": "Smile-cat",
        "image": "https://fonts.gstatic.com/s/e/notoemoji/latest/1f638/emoji.svg"
    },
    {
        "name": "Joy-cat",
        "image": "https://fonts.gstatic.com/s/e/notoemoji/latest/1f639/emoji.svg"
    },
    {
        "name": "Heart-eyes-cat",
        "image": "https://fonts.gstatic.com/s/e/notoemoji/latest/1f63b/emoji.svg"
    },
    {
        "name": "Smirk-cat",
        "image": "https://fonts.gstatic.com/s/e/notoemoji/latest/1f63c/emoji.svg"
    },
    {
        "name": "Kissing-cat",
        "image": "https://fonts.gstatic.com/s/e/notoemoji/latest/1f63d/emoji.svg"
    },
    {
        "name": "Scream-cat",
        "image": "https://fonts.gstatic.com/s/e/notoemoji/latest/1f640/emoji.svg"
    },
    {
        "name": "Crying-cat-face",
        "image": "https://fonts.gstatic.com/s/e/notoemoji/latest/1f63f/emoji.svg"
    },
    {
        "name": "Pouting-cat",
        "image": "https://fonts.gstatic.com/s/e/notoemoji/latest/1f63e/emoji.svg"
    },
    {
        "name": "Glowing-star",
        "image": "https://fonts.gstatic.com/s/e/notoemoji/latest/1f31f/emoji.svg"
    },
    {
        "name": "Sparkles",
        "image": "https://fonts.gstatic.com/s/e/notoemoji/latest/2728/emoji.svg"
    },
    {
        "name": "Collision",
        "image": "https://fonts.gstatic.com/s/e/notoemoji/latest/1f4a5/emoji.svg"
    },
    {
        "name": "Fire",
        "image": "https://fonts.gstatic.com/s/e/notoemoji/latest/1f525/emoji.svg"
    },
    {
        "name": "100",
        "image": "https://fonts.gstatic.com/s/e/notoemoji/latest/1f4af/emoji.svg"
    },
    {
        "name": "Party-popper",
        "image": "https://fonts.gstatic.com/s/e/notoemoji/latest/1f389/emoji.svg"
    },
    {
        "name": "Red-heart",
        "image": "https://fonts.gstatic.com/s/e/notoemoji/latest/2764_fe0f/emoji.svg"
    },
    {
        "name": "Orange-heart",
        "image": "https://fonts.gstatic.com/s/e/notoemoji/latest/1f9e1/emoji.svg"
    },
    {
        "name": "Yellow-heart",
        "image": "https://fonts.gstatic.com/s/e/notoemoji/latest/1f49b/emoji.svg"
    },
    {
        "name": "Green-heart",
        "image": "https://fonts.gstatic.com/s/e/notoemoji/latest/1f49a/emoji.svg"
    },
    {
        "name": "Light-blue-heart",
        "image": "https://fonts.gstatic.com/s/e/notoemoji/latest/1fa75/emoji.svg"
    },
    {
        "name": "Blue-heart",
        "image": "https://fonts.gstatic.com/s/e/notoemoji/latest/1f499/emoji.svg"
    },
    {
        "name": "Purple-heart",
        "image": "https://fonts.gstatic.com/s/e/notoemoji/latest/1f49c/emoji.svg"
    },
    {
        "name": "Brown-heart",
        "image": "https://fonts.gstatic.com/s/e/notoemoji/latest/1f90e/emoji.svg"
    },
    {
        "name": "Black-heart",
        "image": "https://fonts.gstatic.com/s/e/notoemoji/latest/1f5a4/emoji.svg"
    },
    {
        "name": "Grey-heart",
        "image": "https://fonts.gstatic.com/s/e/notoemoji/latest/1fa76/emoji.svg"
    },
    {
        "name": "White-heart",
        "image": "https://fonts.gstatic.com/s/e/notoemoji/latest/1f90d/emoji.svg"
    },
    {
        "name": "Pink-heart",
        "image": "https://fonts.gstatic.com/s/e/notoemoji/latest/1fa77/emoji.svg"
    },
    {
        "name": "Cupid",
        "image": "https://fonts.gstatic.com/s/e/notoemoji/latest/1f498/emoji.svg"
    },
    {
        "name": "Gift-heart",
        "image": "https://fonts.gstatic.com/s/e/notoemoji/latest/1f49d/emoji.svg"
    },
    {
        "name": "Sparkling-heart",
        "image": "https://fonts.gstatic.com/s/e/notoemoji/latest/1f496/emoji.svg"
    },
    {
        "name": "Heart-grow",
        "image": "https://fonts.gstatic.com/s/e/notoemoji/latest/1f497/emoji.svg"
    },
    {
        "name": "Beating-heart",
        "image": "https://fonts.gstatic.com/s/e/notoemoji/latest/1f493/emoji.svg"
    },
    {
        "name": "Revolving-hearts",
        "image": "https://fonts.gstatic.com/s/e/notoemoji/latest/1f49e/emoji.svg"
    },
    {
        "name": "Two-hearts",
        "image": "https://fonts.gstatic.com/s/e/notoemoji/latest/1f495/emoji.svg"
    },
    {
        "name": "Love-letter",
        "image": "https://fonts.gstatic.com/s/e/notoemoji/latest/1f48c/emoji.svg"
    },
    {
        "name": "Heart-box",
        "image": "https://fonts.gstatic.com/s/e/notoemoji/latest/1f49f/emoji.svg"
    },
    {
        "name": "Heart-exclamation-point",
        "image": "https://fonts.gstatic.com/s/e/notoemoji/latest/2763_fe0f/emoji.svg"
    },
    {
        "name": "Bandaged-heart",
        "image": "https://fonts.gstatic.com/s/e/notoemoji/latest/2764_fe0f_200d_1fa79/emoji.svg"
    },
    {
        "name": "Broken-heart",
        "image": "https://fonts.gstatic.com/s/e/notoemoji/latest/1f494/emoji.svg"
    },
    {
        "name": "Fire-heart",
        "image": "https://fonts.gstatic.com/s/e/notoemoji/latest/2764_fe0f_200d_1f525/emoji.svg"
    },
    {
        "name": "Kiss",
        "image": "https://fonts.gstatic.com/s/e/notoemoji/latest/1f48b/emoji.svg"
    },
    {
        "name": "Footprints",
        "image": "https://fonts.gstatic.com/s/e/notoemoji/latest/1f463/emoji.svg"
    },
    {
        "name": "Anatomical-heart",
        "image": "https://fonts.gstatic.com/s/e/notoemoji/latest/1fac0/emoji.svg"
    },
    {
        "name": "Blood",
        "image": "https://fonts.gstatic.com/s/e/notoemoji/latest/1fa78/emoji.svg"
    },
    {
        "name": "Microbe",
        "image": "https://fonts.gstatic.com/s/e/notoemoji/latest/1f9a0/emoji.svg"
    },
    {
        "name": "Eyes",
        "image": "https://fonts.gstatic.com/s/e/notoemoji/latest/1f440/emoji.svg"
    },
    {
        "name": "Eye",
        "image": "https://fonts.gstatic.com/s/e/notoemoji/latest/1f441_fe0f/emoji.svg"
    },
    {
        "name": "Biting-lip",
        "image": "https://fonts.gstatic.com/s/e/notoemoji/latest/1fae6/emoji.svg"
    },
    {
        "name": "Leg-mechanical",
        "image": "https://fonts.gstatic.com/s/e/notoemoji/latest/1f9bf/emoji.svg"
    },
    {
        "name": "Arm-mechanical",
        "image": "https://fonts.gstatic.com/s/e/notoemoji/latest/1f9be/emoji.svg"
    },
    {
        "name": "Muscle",
        "image": "https://fonts.gstatic.com/s/e/notoemoji/latest/1f4aa/emoji.svg"
    },
    {
        "name": "Muscle",
        "image": "https://fonts.gstatic.com/s/e/notoemoji/latest/1f4aa_1f3fb/emoji.svg"
    },
    {
        "name": "Muscle",
        "image": "https://fonts.gstatic.com/s/e/notoemoji/latest/1f4aa_1f3fc/emoji.svg"
    },
    {
        "name": "Muscle",
        "image": "https://fonts.gstatic.com/s/e/notoemoji/latest/1f4aa_1f3fd/emoji.svg"
    },
    {
        "name": "Muscle",
        "image": "https://fonts.gstatic.com/s/e/notoemoji/latest/1f4aa_1f3fe/emoji.svg"
    },
    {
        "name": "Muscle",
        "image": "https://fonts.gstatic.com/s/e/notoemoji/latest/1f4aa_1f3ff/emoji.svg"
    },
    {
        "name": "Clap",
        "image": "https://fonts.gstatic.com/s/e/notoemoji/latest/1f44f/emoji.svg"
    },
    {
        "name": "Clap",
        "image": "https://fonts.gstatic.com/s/e/notoemoji/latest/1f44f_1f3fb/emoji.svg"
    },
    {
        "name": "Clap",
        "image": "https://fonts.gstatic.com/s/e/notoemoji/latest/1f44f_1f3fc/emoji.svg"
    },
    {
        "name": "Clap",
        "image": "https://fonts.gstatic.com/s/e/notoemoji/latest/1f44f_1f3fd/emoji.svg"
    },
    {
        "name": "Clap",
        "image": "https://fonts.gstatic.com/s/e/notoemoji/latest/1f44f_1f3fe/emoji.svg"
    },
    {
        "name": "Clap",
        "image": "https://fonts.gstatic.com/s/e/notoemoji/latest/1f44f_1f3ff/emoji.svg"
    },
    {
        "name": "Thumbs-up",
        "image": "https://fonts.gstatic.com/s/e/notoemoji/latest/1f44d/emoji.svg"
    },
    {
        "name": "Thumbs-up",
        "image": "https://fonts.gstatic.com/s/e/notoemoji/latest/1f44d_1f3fb/emoji.svg"
    },
    {
        "name": "Thumbs-up",
        "image": "https://fonts.gstatic.com/s/e/notoemoji/latest/1f44d_1f3fc/emoji.svg"
    },
    {
        "name": "Thumbs-up",
        "image": "https://fonts.gstatic.com/s/e/notoemoji/latest/1f44d_1f3fd/emoji.svg"
    },
    {
        "name": "Thumbs-up",
        "image": "https://fonts.gstatic.com/s/e/notoemoji/latest/1f44d_1f3fe/emoji.svg"
    },
    {
        "name": "Thumbs-up",
        "image": "https://fonts.gstatic.com/s/e/notoemoji/latest/1f44d_1f3ff/emoji.svg"
    },
    {
        "name": "Thumbs-down",
        "image": "https://fonts.gstatic.com/s/e/notoemoji/latest/1f44e/emoji.svg"
    },
    {
        "name": "Thumbs-down",
        "image": "https://fonts.gstatic.com/s/e/notoemoji/latest/1f44e_1f3fb/emoji.svg"
    },
    {
        "name": "Thumbs-down",
        "image": "https://fonts.gstatic.com/s/e/notoemoji/latest/1f44e_1f3fc/emoji.svg"
    },
    {
        "name": "Thumbs-down",
        "image": "https://fonts.gstatic.com/s/e/notoemoji/latest/1f44e_1f3fd/emoji.svg"
    },
    {
        "name": "Thumbs-down",
        "image": "https://fonts.gstatic.com/s/e/notoemoji/latest/1f44e_1f3fe/emoji.svg"
    },
    {
        "name": "Thumbs-down",
        "image": "https://fonts.gstatic.com/s/e/notoemoji/latest/1f44e_1f3ff/emoji.svg"
    },
    {
        "name": "Raising-hands",
        "image": "https://fonts.gstatic.com/s/e/notoemoji/latest/1f64c/emoji.svg"
    },
    {
        "name": "Raising-hands",
        "image": "https://fonts.gstatic.com/s/e/notoemoji/latest/1f64c_1f3fb/emoji.svg"
    },
    {
        "name": "Raising-hands",
        "image": "https://fonts.gstatic.com/s/e/notoemoji/latest/1f64c_1f3fc/emoji.svg"
    },
    {
        "name": "Raising-hands",
        "image": "https://fonts.gstatic.com/s/e/notoemoji/latest/1f64c_1f3fd/emoji.svg"
    },
    {
        "name": "Raising-hands",
        "image": "https://fonts.gstatic.com/s/e/notoemoji/latest/1f64c_1f3fe/emoji.svg"
    },
    {
        "name": "Raising-hands",
        "image": "https://fonts.gstatic.com/s/e/notoemoji/latest/1f64c_1f3ff/emoji.svg"
    },
    {
        "name": "Wave",
        "image": "https://fonts.gstatic.com/s/e/notoemoji/latest/1f44b/emoji.svg"
    },
    {
        "name": "Wave",
        "image": "https://fonts.gstatic.com/s/e/notoemoji/latest/1f44b_1f3fb/emoji.svg"
    },
    {
        "name": "Wave",
        "image": "https://fonts.gstatic.com/s/e/notoemoji/latest/1f44b_1f3fc/emoji.svg"
    },
    {
        "name": "Wave",
        "image": "https://fonts.gstatic.com/s/e/notoemoji/latest/1f44b_1f3fd/emoji.svg"
    },
    {
        "name": "Wave",
        "image": "https://fonts.gstatic.com/s/e/notoemoji/latest/1f44b_1f3fe/emoji.svg"
    },
    {
        "name": "Wave",
        "image": "https://fonts.gstatic.com/s/e/notoemoji/latest/1f44b_1f3ff/emoji.svg"
    },
    {
        "name": "Victory",
        "image": "https://fonts.gstatic.com/s/e/notoemoji/latest/270c_fe0f/emoji.svg"
    },
    {
        "name": "Victory",
        "image": "https://fonts.gstatic.com/s/e/notoemoji/latest/270c_1f3fb/emoji.svg"
    },
    {
        "name": "Victory",
        "image": "https://fonts.gstatic.com/s/e/notoemoji/latest/270c_1f3fc/emoji.svg"
    },
    {
        "name": "Victory",
        "image": "https://fonts.gstatic.com/s/e/notoemoji/latest/270c_1f3fd/emoji.svg"
    },
    {
        "name": "Victory",
        "image": "https://fonts.gstatic.com/s/e/notoemoji/latest/270c_1f3fe/emoji.svg"
    },
    {
        "name": "Victory",
        "image": "https://fonts.gstatic.com/s/e/notoemoji/latest/270c_1f3ff/emoji.svg"
    },
    {
        "name": "Crossed-fingers",
        "image": "https://fonts.gstatic.com/s/e/notoemoji/latest/1f91e/emoji.svg"
    },
    {
        "name": "Crossed-fingers",
        "image": "https://fonts.gstatic.com/s/e/notoemoji/latest/1f91e_1f3fb/emoji.svg"
    },
    {
        "name": "Crossed-fingers",
        "image": "https://fonts.gstatic.com/s/e/notoemoji/latest/1f91e_1f3fc/emoji.svg"
    },
    {
        "name": "Crossed-fingers",
        "image": "https://fonts.gstatic.com/s/e/notoemoji/latest/1f91e_1f3fd/emoji.svg"
    },
    {
        "name": "Crossed-fingers",
        "image": "https://fonts.gstatic.com/s/e/notoemoji/latest/1f91e_1f3fe/emoji.svg"
    },
    {
        "name": "Crossed-fingers",
        "image": "https://fonts.gstatic.com/s/e/notoemoji/latest/1f91e_1f3ff/emoji.svg"
    },
    {
        "name": "Index-finger",
        "image": "https://fonts.gstatic.com/s/e/notoemoji/latest/261d_fe0f/emoji.svg"
    },
    {
        "name": "Index-finger",
        "image": "https://fonts.gstatic.com/s/e/notoemoji/latest/261d_1f3fb/emoji.svg"
    },
    {
        "name": "Index-finger",
        "image": "https://fonts.gstatic.com/s/e/notoemoji/latest/261d_1f3fc/emoji.svg"
    },
    {
        "name": "Index-finger",
        "image": "https://fonts.gstatic.com/s/e/notoemoji/latest/261d_1f3fd/emoji.svg"
    },
    {
        "name": "Index-finger",
        "image": "https://fonts.gstatic.com/s/e/notoemoji/latest/261d_1f3fe/emoji.svg"
    },
    {
        "name": "Index-finger",
        "image": "https://fonts.gstatic.com/s/e/notoemoji/latest/261d_1f3ff/emoji.svg"
    },
    {
        "name": "Folded-hands",
        "image": "https://fonts.gstatic.com/s/e/notoemoji/latest/1f64f/emoji.svg"
    },
    {
        "name": "Folded-hands",
        "image": "https://fonts.gstatic.com/s/e/notoemoji/latest/1f64f_1f3fb/emoji.svg"
    },
    {
        "name": "Folded-hands",
        "image": "https://fonts.gstatic.com/s/e/notoemoji/latest/1f64f_1f3fc/emoji.svg"
    },
    {
        "name": "Folded-hands",
        "image": "https://fonts.gstatic.com/s/e/notoemoji/latest/1f64f_1f3fd/emoji.svg"
    },
    {
        "name": "Folded-hands",
        "image": "https://fonts.gstatic.com/s/e/notoemoji/latest/1f64f_1f3fe/emoji.svg"
    },
    {
        "name": "Folded-hands",
        "image": "https://fonts.gstatic.com/s/e/notoemoji/latest/1f64f_1f3ff/emoji.svg"
    }
]